oracle_predeployed/__init__.py
oracle_predeployed/address.py
oracle_predeployed/oracle_generator.py
oracle_predeployed/oracle_upgradeable_generator.py
oracle_predeployed/py.typed
oracle_predeployed/artifacts/.keep
oracle_predeployed/artifacts/Oracle.json
oracle_predeployed/artifacts/OracleUpgradeable.json
oracle_predeployed-1.0.0a4.dist-info/METADATA
oracle_predeployed-1.0.0a4.dist-info/WHEEL
oracle_predeployed-1.0.0a4.dist-info/top_level.txt
oracle_predeployed-1.0.0a4.dist-info/RECORD
