Metadata-Version: 2.1
Name: oracle-predeployed
Version: 1.0.0a4
Summary: A tool for generating predeployed oracle smart contract
Home-page: https://github.com/skalenetwork/oracle-contract
Author: Artem Payvin
Author-email: artem.payvin@skalelabs.com
Classifier: Programming Language :: Python :: 3
Classifier: License :: OSI Approved :: GNU Affero General Public License v3
Classifier: Operating System :: OS Independent
Requires-Python: >=3.7
Requires-Dist: predeployed-generator
